nodestream_plugin_k8s/__init__.py
nodestream_plugin_k8s/commands/__init__.py
nodestream_plugin_k8s/commands/destroy_command.py
nodestream_plugin_k8s/commands/list_command.py
nodestream_plugin_k8s/commands/sync_command.py
nodestream_plugin_k8s/operations/__init__.py
nodestream_plugin_k8s/project_resource_manager.py
nodestream_plugin_k8s-0.14.0.dist-info/LICENSE
nodestream_plugin_k8s-0.14.0.dist-info/METADATA
nodestream_plugin_k8s-0.14.0.dist-info/WHEEL
nodestream_plugin_k8s-0.14.0.dist-info/entry_points.txt
nodestream_plugin_k8s-0.14.0.dist-info/RECORD
