Metadata-Version: 2.3
Name: nodestream-plugin-k8s
Version: 0.14.0
Summary: A plugin for nodestream that manages k8s resources.
License: Apache 2.0
Author: Zach Probst
Author-email: Zach_Probst@intuit.com
Requires-Python: >=3.10,<4.0
Classifier: License :: Other/Proprietary License
Classifier: Programming Language :: Python :: 3
Classifier: Programming Language :: Python :: 3.10
Classifier: Programming Language :: Python :: 3.11
Classifier: Programming Language :: Python :: 3.12
Classifier: Programming Language :: Python :: 3.13
Requires-Dist: nodestream (>=0.14.0,<0.15.0)
